[
    {
        "gameRaw": {
            "gamePk": 824686,
            "gameGuid": "0ad9f607-d175-409c-98e5-7eb5f9b63fbc",
            "link": "/api/v1.1/game/824686/feed/live",
            "gameType": "R",
            "season": "2026",
            "gameDate": "2026-05-01T18:20:00Z",
            "officialDate": "2026-05-01",
            "status": {
                "abstractGameState": "Preview",
                "codedGameState": "S",
                "detailedState": "Scheduled",
                "statusCode": "S",
                "startTimeTBD": false,
                "abstractGameCode": "P"
            },
            "teams": {
                "away": {
                    "team": {
                        "id": 109,
                        "name": "Arizona Diamondbacks",
                        "link": "/api/v1/teams/109"
                    },
                    "leagueRecord": {
                        "wins": 14,
                        "losses": 12,
                        "pct": ".538"
                    },
                    "splitSquad": false,
                    "seriesNumber": 11
                },
                "home": {
                    "team": {
                        "id": 112,
                        "name": "Chicago Cubs",
                        "link": "/api/v1/teams/112"
                    },
                    "leagueRecord": {
                        "wins": 17,
                        "losses": 9,
                        "pct": ".654"
                    },
                    "splitSquad": false,
                    "seriesNumber": 11
                }
            },
            "linescore": {
                "scheduledInnings": 9,
                "innings": [],
                "teams": {
                    "home": {},
                    "away": {}
                },
                "defense": {
                    "team": {
                        "id": 112,
                        "name": "Chicago Cubs",
                        "link": "/api/v1/teams/112"
                    }
                },
                "offense": {
                    "team": {
                        "id": 109,
                        "name": "Arizona Diamondbacks",
                        "link": "/api/v1/teams/109"
                    }
                }
            },
            "venue": {
                "id": 17,
                "name": "Wrigley Field",
                "link": "/api/v1/venues/17",
                "active": true,
                "season": "2026"
            },
            "content": {
                "link": "/api/v1/game/824686/content"
            },
            "gameNumber": 1,
            "publicFacing": true,
            "doubleHeader": "N",
            "gamedayType": "P",
            "tiebreaker": "N",
            "calendarEventID": "14-824686-2026-05-01",
            "seasonDisplay": "2026",
            "dayNight": "day",
            "scheduledInnings": 9,
            "reverseHomeAwayStatus": false,
            "inningBreakLength": 120,
            "gamesInSeries": 3,
            "seriesGameNumber": 1,
            "seriesDescription": "Regular Season",
            "recordSource": "S",
            "ifNecessary": "N",
            "ifNecessaryDescription": "Normal Game"
        },
        "stadium": {
            "id": 17,
            "name": "Wrigley Field",
            "team": "Chicago Cubs",
            "lat": 41.9484,
            "lon": -87.6553,
            "bearing": 37
        },
        "odds": null,
        "weather": {
            "status": "ok",
            "lastUpdated": 1777133737.507476,
            "temp": 42,
            "humidity": 50,
            "maxPrecipChance": 0,
            "isThunderstorm": false,
            "isSnow": false,
            "windSpeed": 11,
            "windDir": 37,
            "hourly": [
                {
                    "timestamp": "2026-05-01T17:00Z",
                    "temp": 42,
                    "precipChance": 0,
                    "isThunderstorm": false,
                    "isSnow": false
                },
                {
                    "timestamp": "2026-05-01T18:00Z",
                    "temp": 42,
                    "precipChance": 0,
                    "isThunderstorm": false,
                    "isSnow": false
                },
                {
                    "timestamp": "2026-05-01T19:00Z",
                    "temp": 43,
                    "precipChance": 0,
                    "isThunderstorm": false,
                    "isSnow": false
                },
                {
                    "timestamp": "2026-05-01T20:00Z",
                    "temp": 44,
                    "precipChance": 0,
                    "isThunderstorm": false,
                    "isSnow": false
                },
                {
                    "timestamp": "2026-05-01T21:00Z",
                    "temp": 45,
                    "precipChance": 0,
                    "isThunderstorm": false,
                    "isSnow": false
                }
            ]
        },
        "wind": {
            "text": "Blowing IN",
            "cssClass": "bg-in",
            "arrow": "\u2b07"
        },
        "roof": false,
        "roofPending": false,
        "lineupHandedness": {},
        "lineupPositions": {}
    },
    {
        "gameRaw": {
            "gamePk": 824287,
            "gameGuid": "ddd3d490-55b2-49ee-a27b-87be7b179e6e",
            "link": "/api/v1.1/game/824287/feed/live",
            "gameType": "R",
            "season": "2026",
            "gameDate": "2026-05-01T22:40:00Z",
            "officialDate": "2026-05-01",
            "status": {
                "abstractGameState": "Preview",
                "codedGameState": "S",
                "detailedState": "Scheduled",
                "statusCode": "S",
                "startTimeTBD": false,
                "abstractGameCode": "P"
            },
            "teams": {
                "away": {
                    "team": {
                        "id": 140,
                        "name": "Texas Rangers",
                        "link": "/api/v1/teams/140"
                    },
                    "leagueRecord": {
                        "wins": 13,
                        "losses": 13,
                        "pct": ".500"
                    },
                    "splitSquad": false,
                    "seriesNumber": 11
                },
                "home": {
                    "team": {
                        "id": 116,
                        "name": "Detroit Tigers",
                        "link": "/api/v1/teams/116"
                    },
                    "leagueRecord": {
                        "wins": 14,
                        "losses": 13,
                        "pct": ".519"
                    },
                    "splitSquad": false,
                    "seriesNumber": 11
                }
            },
            "linescore": {
                "scheduledInnings": 9,
                "innings": [],
                "teams": {
                    "home": {},
                    "away": {}
                },
                "defense": {
                    "team": {
                        "id": 116,
                        "name": "Detroit Tigers",
                        "link": "/api/v1/teams/116"
                    }
                },
                "offense": {
                    "team": {
                        "id": 140,
                        "name": "Texas Rangers",
                        "link": "/api/v1/teams/140"
                    }
                }
            },
            "venue": {
                "id": 2394,
                "name": "Comerica Park",
                "link": "/api/v1/venues/2394",
                "active": true,
                "season": "2026"
            },
            "content": {
                "link": "/api/v1/game/824287/content"
            },
            "gameNumber": 1,
            "publicFacing": true,
            "doubleHeader": "N",
            "gamedayType": "P",
            "tiebreaker": "N",
            "calendarEventID": "14-824287-2026-05-01",
            "seasonDisplay": "2026",
            "dayNight": "night",
            "scheduledInnings": 9,
            "reverseHomeAwayStatus": false,
            "inningBreakLength": 120,
            "gamesInSeries": 3,
            "seriesGameNumber": 1,
            "seriesDescription": "Regular Season",
            "recordSource": "S",
            "ifNecessary": "N",
            "ifNecessaryDescription": "Normal Game"
        },
        "stadium": {
            "id": 2394,
            "name": "Comerica Park",
            "team": "Detroit Tigers",
            "lat": 42.339,
            "lon": -83.0485,
            "bearing": 150
        },
        "odds": null,
        "weather": {
            "status": "ok",
            "lastUpdated": 1777133738.62113,
            "temp": 53,
            "humidity": 30,
            "maxPrecipChance": 0,
            "isThunderstorm": false,
            "isSnow": false,
            "windSpeed": 12,
            "windDir": 310,
            "hourly": [
                {
                    "timestamp": "2026-05-01T21:00Z",
                    "temp": 54,
                    "precipChance": 0,
                    "isThunderstorm": false,
                    "isSnow": false
                },
                {
                    "timestamp": "2026-05-01T22:00Z",
                    "temp": 53,
                    "precipChance": 0,
                    "isThunderstorm": false,
                    "isSnow": false
                },
                {
                    "timestamp": "2026-05-01T23:00Z",
                    "temp": 52,
                    "precipChance": 0,
                    "isThunderstorm": false,
                    "isSnow": false
                },
                {
                    "timestamp": "2026-05-02T00:00Z",
                    "temp": 50,
                    "precipChance": 0,
                    "isThunderstorm": false,
                    "isSnow": false
                },
                {
                    "timestamp": "2026-05-02T01:00Z",
                    "temp": 49,
                    "precipChance": 0,
                    "isThunderstorm": false,
                    "isSnow": false
                }
            ]
        },
        "wind": {
            "text": "Blowing OUT",
            "cssClass": "bg-out",
            "arrow": "\u2b06"
        },
        "roof": false,
        "roofPending": false,
        "lineupHandedness": {},
        "lineupPositions": {}
    },
    {
        "gameRaw": {
            "gamePk": 823389,
            "gameGuid": "0385f8c4-8430-459f-91ff-0b67a321232a",
            "link": "/api/v1.1/game/823389/feed/live",
            "gameType": "R",
            "season": "2026",
            "gameDate": "2026-05-01T22:45:00Z",
            "officialDate": "2026-05-01",
            "status": {
                "abstractGameState": "Preview",
                "codedGameState": "S",
                "detailedState": "Scheduled",
                "statusCode": "S",
                "startTimeTBD": false,
                "abstractGameCode": "P"
            },
            "teams": {
                "away": {
                    "team": {
                        "id": 113,
                        "name": "Cincinnati Reds",
                        "link": "/api/v1/teams/113"
                    },
                    "leagueRecord": {
                        "wins": 17,
                        "losses": 9,
                        "pct": ".654"
                    },
                    "splitSquad": false,
                    "seriesNumber": 11
                },
                "home": {
                    "team": {
                        "id": 134,
                        "name": "Pittsburgh Pirates",
                        "link": "/api/v1/teams/134"
                    },
                    "leagueRecord": {
                        "wins": 15,
                        "losses": 11,
                        "pct": ".577"
                    },
                    "splitSquad": false,
                    "seriesNumber": 11
                }
            },
            "linescore": {
                "scheduledInnings": 9,
                "innings": [],
                "teams": {
                    "home": {},
                    "away": {}
                },
                "defense": {
                    "team": {
                        "id": 113,
                        "name": "Cincinnati Reds",
                        "link": "/api/v1/teams/113"
                    }
                },
                "offense": {
                    "team": {
                        "id": 134,
                        "name": "Pittsburgh Pirates",
                        "link": "/api/v1/teams/134"
                    }
                }
            },
            "venue": {
                "id": 31,
                "name": "PNC Park",
                "link": "/api/v1/venues/31",
                "active": true,
                "season": "2026"
            },
            "content": {
                "link": "/api/v1/game/823389/content"
            },
            "gameNumber": 1,
            "publicFacing": true,
            "doubleHeader": "N",
            "gamedayType": "P",
            "tiebreaker": "N",
            "calendarEventID": "14-823389-2026-05-01",
            "seasonDisplay": "2026",
            "dayNight": "night",
            "scheduledInnings": 9,
            "reverseHomeAwayStatus": false,
            "inningBreakLength": 145,
            "gamesInSeries": 3,
            "seriesGameNumber": 1,
            "seriesDescription": "Regular Season",
            "recordSource": "S",
            "ifNecessary": "N",
            "ifNecessaryDescription": "Normal Game",
            "lineups": {}
        },
        "stadium": {
            "id": 31,
            "name": "PNC Park",
            "team": "Pittsburgh Pirates",
            "lat": 40.4469,
            "lon": -80.0057,
            "bearing": 116
        },
        "odds": null,
        "weather": {
            "status": "ok",
            "lastUpdated": 1777133739.734457,
            "temp": 50,
            "humidity": 41,
            "maxPrecipChance": 0,
            "isThunderstorm": false,
            "isSnow": false,
            "windSpeed": 12,
            "windDir": 304,
            "hourly": [
                {
                    "timestamp": "2026-05-01T21:00Z",
                    "temp": 52,
                    "precipChance": 0,
                    "isThunderstorm": false,
                    "isSnow": false
                },
                {
                    "timestamp": "2026-05-01T22:00Z",
                    "temp": 50,
                    "precipChance": 0,
                    "isThunderstorm": false,
                    "isSnow": false
                },
                {
                    "timestamp": "2026-05-01T23:00Z",
                    "temp": 48,
                    "precipChance": 0,
                    "isThunderstorm": false,
                    "isSnow": false
                },
                {
                    "timestamp": "2026-05-02T00:00Z",
                    "temp": 46,
                    "precipChance": 0,
                    "isThunderstorm": false,
                    "isSnow": false
                },
                {
                    "timestamp": "2026-05-02T01:00Z",
                    "temp": 44,
                    "precipChance": 0,
                    "isThunderstorm": false,
                    "isSnow": false
                }
            ]
        },
        "wind": {
            "text": "Blowing OUT",
            "cssClass": "bg-out",
            "arrow": "\u2b06"
        },
        "roof": false,
        "roofPending": false,
        "lineupHandedness": {},
        "lineupPositions": {}
    },
    {
        "gameRaw": {
            "gamePk": 822744,
            "gameGuid": "96c2a4e3-55c1-448f-a7ce-cfd1be53c5eb",
            "link": "/api/v1.1/game/822744/feed/live",
            "gameType": "R",
            "season": "2026",
            "gameDate": "2026-05-01T22:45:00Z",
            "officialDate": "2026-05-01",
            "status": {
                "abstractGameState": "Preview",
                "codedGameState": "S",
                "detailedState": "Scheduled",
                "statusCode": "S",
                "startTimeTBD": false,
                "abstractGameCode": "P"
            },
            "teams": {
                "away": {
                    "team": {
                        "id": 158,
                        "name": "Milwaukee Brewers",
                        "link": "/api/v1/teams/158"
                    },
                    "leagueRecord": {
                        "wins": 13,
                        "losses": 12,
                        "pct": ".520"
                    },
                    "splitSquad": false,
                    "seriesNumber": 11
                },
                "home": {
                    "team": {
                        "id": 120,
                        "name": "Washington Nationals",
                        "link": "/api/v1/teams/120"
                    },
                    "leagueRecord": {
                        "wins": 12,
                        "losses": 16,
                        "pct": ".429"
                    },
                    "splitSquad": false,
                    "seriesNumber": 11
                }
            },
            "linescore": {
                "scheduledInnings": 9,
                "innings": [],
                "teams": {
                    "home": {},
                    "away": {}
                },
                "defense": {
                    "team": {
                        "id": 120,
                        "name": "Washington Nationals",
                        "link": "/api/v1/teams/120"
                    }
                },
                "offense": {
                    "team": {
                        "id": 158,
                        "name": "Milwaukee Brewers",
                        "link": "/api/v1/teams/158"
                    }
                }
            },
            "venue": {
                "id": 3309,
                "name": "Nationals Park",
                "link": "/api/v1/venues/3309",
                "active": true,
                "season": "2026"
            },
            "content": {
                "link": "/api/v1/game/822744/content"
            },
            "gameNumber": 1,
            "publicFacing": true,
            "doubleHeader": "N",
            "gamedayType": "P",
            "tiebreaker": "N",
            "calendarEventID": "14-822744-2026-05-01",
            "seasonDisplay": "2026",
            "dayNight": "night",
            "scheduledInnings": 9,
            "reverseHomeAwayStatus": false,
            "inningBreakLength": 120,
            "gamesInSeries": 3,
            "seriesGameNumber": 1,
            "seriesDescription": "Regular Season",
            "recordSource": "S",
            "ifNecessary": "N",
            "ifNecessaryDescription": "Normal Game"
        },
        "stadium": {
            "id": 3309,
            "name": "Nationals Park",
            "team": "Washington Nationals",
            "lat": 38.873,
            "lon": -77.0074,
            "bearing": 30
        },
        "odds": null,
        "weather": {
            "status": "ok",
            "lastUpdated": 1777133740.847875,
            "temp": 59,
            "humidity": 32,
            "maxPrecipChance": 0,
            "isThunderstorm": false,
            "isSnow": false,
            "windSpeed": 13,
            "windDir": 300,
            "hourly": [
                {
                    "timestamp": "2026-05-01T21:00Z",
                    "temp": 60,
                    "precipChance": 0,
                    "isThunderstorm": false,
                    "isSnow": false
                },
                {
                    "timestamp": "2026-05-01T22:00Z",
                    "temp": 59,
                    "precipChance": 0,
                    "isThunderstorm": false,
                    "isSnow": false
                },
                {
                    "timestamp": "2026-05-01T23:00Z",
                    "temp": 57,
                    "precipChance": 0,
                    "isThunderstorm": false,
                    "isSnow": false
                },
                {
                    "timestamp": "2026-05-02T00:00Z",
                    "temp": 55,
                    "precipChance": 0,
                    "isThunderstorm": false,
                    "isSnow": false
                },
                {
                    "timestamp": "2026-05-02T01:00Z",
                    "temp": 53,
                    "precipChance": 0,
                    "isThunderstorm": false,
                    "isSnow": false
                }
            ]
        },
        "wind": {
            "text": "Cross (L to R)",
            "cssClass": "bg-cross",
            "arrow": "\u27a1"
        },
        "roof": false,
        "roofPending": false,
        "lineupHandedness": {},
        "lineupPositions": {}
    },
    {
        "gameRaw": {
            "gamePk": 823557,
            "gameGuid": "3e2a6adc-cba1-4c9a-93e5-20cea322f064",
            "link": "/api/v1.1/game/823557/feed/live",
            "gameType": "R",
            "season": "2026",
            "gameDate": "2026-05-01T23:05:00Z",
            "officialDate": "2026-05-01",
            "status": {
                "abstractGameState": "Preview",
                "codedGameState": "S",
                "detailedState": "Scheduled",
                "statusCode": "S",
                "startTimeTBD": false,
                "abstractGameCode": "P"
            },
            "teams": {
                "away": {
                    "team": {
                        "id": 110,
                        "name": "Baltimore Orioles",
                        "link": "/api/v1/teams/110"
                    },
                    "leagueRecord": {
                        "wins": 13,
                        "losses": 14,
                        "pct": ".481"
                    },
                    "splitSquad": false,
                    "seriesNumber": 11
                },
                "home": {
                    "team": {
                        "id": 147,
                        "name": "New York Yankees",
                        "link": "/api/v1/teams/147"
                    },
                    "leagueRecord": {
                        "wins": 17,
                        "losses": 9,
                        "pct": ".654"
                    },
                    "splitSquad": false,
                    "seriesNumber": 11
                }
            },
            "linescore": {
                "scheduledInnings": 9,
                "innings": [],
                "teams": {
                    "home": {},
                    "away": {}
                },
                "defense": {
                    "team": {
                        "id": 147,
                        "name": "New York Yankees",
                        "link": "/api/v1/teams/147"
                    }
                },
                "offense": {
                    "team": {
                        "id": 110,
                        "name": "Baltimore Orioles",
                        "link": "/api/v1/teams/110"
                    }
                }
            },
            "venue": {
                "id": 3313,
                "name": "Yankee Stadium",
                "link": "/api/v1/venues/3313",
                "active": true,
                "season": "2026"
            },
            "content": {
                "link": "/api/v1/game/823557/content"
            },
            "gameNumber": 1,
            "publicFacing": true,
            "doubleHeader": "N",
            "gamedayType": "P",
            "tiebreaker": "N",
            "calendarEventID": "14-823557-2026-05-01",
            "seasonDisplay": "2026",
            "dayNight": "night",
            "scheduledInnings": 9,
            "reverseHomeAwayStatus": false,
            "inningBreakLength": 120,
            "gamesInSeries": 4,
            "seriesGameNumber": 1,
            "seriesDescription": "Regular Season",
            "recordSource": "S",
            "ifNecessary": "N",
            "ifNecessaryDescription": "Normal Game"
        },
        "stadium": {
            "id": 3313,
            "name": "Yankee Stadium",
            "team": "New York Yankees",
            "lat": 40.8296,
            "lon": -73.9262,
            "bearing": 75
        },
        "odds": null,
        "weather": {
            "status": "ok",
            "lastUpdated": 1777133741.961712,
            "temp": 50,
            "humidity": 53,
            "maxPrecipChance": 0,
            "isThunderstorm": false,
            "isSnow": false,
            "windSpeed": 16,
            "windDir": 306,
            "hourly": [
                {
                    "timestamp": "2026-05-01T22:00Z",
                    "temp": 52,
                    "precipChance": 0,
                    "isThunderstorm": false,
                    "isSnow": false
                },
                {
                    "timestamp": "2026-05-01T23:00Z",
                    "temp": 50,
                    "precipChance": 0,
                    "isThunderstorm": false,
                    "isSnow": false
                },
                {
                    "timestamp": "2026-05-02T00:00Z",
                    "temp": 49,
                    "precipChance": 0,
                    "isThunderstorm": false,
                    "isSnow": false
                },
                {
                    "timestamp": "2026-05-02T01:00Z",
                    "temp": 48,
                    "precipChance": 0,
                    "isThunderstorm": false,
                    "isSnow": false
                },
                {
                    "timestamp": "2026-05-02T02:00Z",
                    "temp": 47,
                    "precipChance": 0,
                    "isThunderstorm": false,
                    "isSnow": false
                }
            ]
        },
        "wind": {
            "text": "Out to Right",
            "cssClass": "bg-out",
            "arrow": "\u2197"
        },
        "roof": false,
        "roofPending": false,
        "lineupHandedness": {},
        "lineupPositions": {}
    },
    {
        "gameRaw": {
            "gamePk": 824772,
            "gameGuid": "a465d8aa-6d60-4536-8e82-998a6d71d0c9",
            "link": "/api/v1.1/game/824772/feed/live",
            "gameType": "R",
            "season": "2026",
            "gameDate": "2026-05-01T23:10:00Z",
            "officialDate": "2026-05-01",
            "status": {
                "abstractGameState": "Preview",
                "codedGameState": "S",
                "detailedState": "Scheduled",
                "statusCode": "S",
                "startTimeTBD": false,
                "abstractGameCode": "P"
            },
            "teams": {
                "away": {
                    "team": {
                        "id": 117,
                        "name": "Houston Astros",
                        "link": "/api/v1/teams/117"
                    },
                    "leagueRecord": {
                        "wins": 10,
                        "losses": 17,
                        "pct": ".370"
                    },
                    "splitSquad": false,
                    "seriesNumber": 11
                },
                "home": {
                    "team": {
                        "id": 111,
                        "name": "Boston Red Sox",
                        "link": "/api/v1/teams/111"
                    },
                    "leagueRecord": {
                        "wins": 10,
                        "losses": 17,
                        "pct": ".370"
                    },
                    "splitSquad": false,
                    "seriesNumber": 11
                }
            },
            "linescore": {
                "scheduledInnings": 9,
                "innings": [],
                "teams": {
                    "home": {},
                    "away": {}
                },
                "defense": {
                    "team": {
                        "id": 111,
                        "name": "Boston Red Sox",
                        "link": "/api/v1/teams/111"
                    }
                },
                "offense": {
                    "team": {
                        "id": 117,
                        "name": "Houston Astros",
                        "link": "/api/v1/teams/117"
                    }
                }
            },
            "venue": {
                "id": 3,
                "name": "Fenway Park",
                "link": "/api/v1/venues/3",
                "active": true,
                "season": "2026"
            },
            "content": {
                "link": "/api/v1/game/824772/content"
            },
            "gameNumber": 1,
            "publicFacing": true,
            "doubleHeader": "N",
            "gamedayType": "P",
            "tiebreaker": "N",
            "calendarEventID": "14-824772-2026-05-01",
            "seasonDisplay": "2026",
            "dayNight": "night",
            "scheduledInnings": 9,
            "reverseHomeAwayStatus": false,
            "inningBreakLength": 120,
            "gamesInSeries": 3,
            "seriesGameNumber": 1,
            "seriesDescription": "Regular Season",
            "recordSource": "S",
            "ifNecessary": "N",
            "ifNecessaryDescription": "Normal Game"
        },
        "stadium": {
            "id": 3,
            "name": "Fenway Park",
            "team": "Boston Red Sox",
            "lat": 42.3467,
            "lon": -71.0972,
            "bearing": 45
        },
        "odds": null,
        "weather": {
            "status": "ok",
            "lastUpdated": 1777133743.075182,
            "temp": 45,
            "humidity": 93,
            "maxPrecipChance": 15,
            "isThunderstorm": false,
            "isSnow": false,
            "windSpeed": 8,
            "windDir": 326,
            "hourly": [
                {
                    "timestamp": "2026-05-01T22:00Z",
                    "temp": 45,
                    "precipChance": 15,
                    "isThunderstorm": false,
                    "isSnow": false
                },
                {
                    "timestamp": "2026-05-01T23:00Z",
                    "temp": 45,
                    "precipChance": 15,
                    "isThunderstorm": false,
                    "isSnow": false
                },
                {
                    "timestamp": "2026-05-02T00:00Z",
                    "temp": 45,
                    "precipChance": 15,
                    "isThunderstorm": false,
                    "isSnow": false
                },
                {
                    "timestamp": "2026-05-02T01:00Z",
                    "temp": 44,
                    "precipChance": 15,
                    "isThunderstorm": false,
                    "isSnow": false
                },
                {
                    "timestamp": "2026-05-02T02:00Z",
                    "temp": 44,
                    "precipChance": 15,
                    "isThunderstorm": false,
                    "isSnow": false
                }
            ]
        },
        "wind": {
            "text": "Cross (L to R)",
            "cssClass": "bg-cross",
            "arrow": "\u27a1"
        },
        "roof": false,
        "roofPending": false,
        "lineupHandedness": {},
        "lineupPositions": {}
    },
    {
        "gameRaw": {
            "gamePk": 822990,
            "gameGuid": "b5029d46-4dfd-4ab9-b5c4-6b9296c0e231",
            "link": "/api/v1.1/game/822990/feed/live",
            "gameType": "R",
            "season": "2026",
            "gameDate": "2026-05-01T23:10:00Z",
            "officialDate": "2026-05-01",
            "status": {
                "abstractGameState": "Preview",
                "codedGameState": "S",
                "detailedState": "Scheduled",
                "statusCode": "S",
                "startTimeTBD": false,
                "abstractGameCode": "P"
            },
            "teams": {
                "away": {
                    "team": {
                        "id": 137,
                        "name": "San Francisco Giants",
                        "link": "/api/v1/teams/137"
                    },
                    "leagueRecord": {
                        "wins": 12,
                        "losses": 15,
                        "pct": ".444"
                    },
                    "splitSquad": false,
                    "seriesNumber": 11
                },
                "home": {
                    "team": {
                        "id": 139,
                        "name": "Tampa Bay Rays",
                        "link": "/api/v1/teams/139"
                    },
                    "leagueRecord": {
                        "wins": 15,
                        "losses": 11,
                        "pct": ".577"
                    },
                    "splitSquad": false,
                    "seriesNumber": 11
                }
            },
            "linescore": {
                "scheduledInnings": 9,
                "innings": [],
                "teams": {
                    "home": {},
                    "away": {}
                },
                "defense": {
                    "team": {
                        "id": 139,
                        "name": "Tampa Bay Rays",
                        "link": "/api/v1/teams/139"
                    }
                },
                "offense": {
                    "team": {
                        "id": 137,
                        "name": "San Francisco Giants",
                        "link": "/api/v1/teams/137"
                    }
                }
            },
            "venue": {
                "id": 12,
                "name": "Tropicana Field",
                "link": "/api/v1/venues/12",
                "active": true,
                "season": "2026"
            },
            "content": {
                "link": "/api/v1/game/822990/content"
            },
            "gameNumber": 1,
            "publicFacing": true,
            "doubleHeader": "N",
            "gamedayType": "P",
            "tiebreaker": "N",
            "calendarEventID": "14-822990-2026-05-01",
            "seasonDisplay": "2026",
            "dayNight": "night",
            "scheduledInnings": 9,
            "reverseHomeAwayStatus": false,
            "inningBreakLength": 120,
            "gamesInSeries": 3,
            "seriesGameNumber": 1,
            "seriesDescription": "Regular Season",
            "recordSource": "S",
            "ifNecessary": "N",
            "ifNecessaryDescription": "Normal Game"
        },
        "stadium": {
            "id": 12,
            "name": "Tropicana Field",
            "team": "Tampa Bay Rays",
            "lat": 27.7682,
            "lon": -82.6534,
            "bearing": 0,
            "roof": true,
            "dome": true
        },
        "odds": null,
        "weather": {
            "status": "ok",
            "lastUpdated": 1777133744.189619,
            "temp": 78,
            "humidity": 61,
            "maxPrecipChance": 0,
            "isThunderstorm": false,
            "isSnow": false,
            "windSpeed": 0,
            "windDir": 242,
            "hourly": [
                {
                    "timestamp": "2026-05-01T22:00Z",
                    "temp": 80,
                    "precipChance": 0,
                    "isThunderstorm": false,
                    "isSnow": false
                },
                {
                    "timestamp": "2026-05-01T23:00Z",
                    "temp": 78,
                    "precipChance": 0,
                    "isThunderstorm": false,
                    "isSnow": false
                },
                {
                    "timestamp": "2026-05-02T00:00Z",
                    "temp": 77,
                    "precipChance": 0,
                    "isThunderstorm": false,
                    "isSnow": false
                },
                {
                    "timestamp": "2026-05-02T01:00Z",
                    "temp": 76,
                    "precipChance": 0,
                    "isThunderstorm": false,
                    "isSnow": false
                },
                {
                    "timestamp": "2026-05-02T02:00Z",
                    "temp": 76,
                    "precipChance": 0,
                    "isThunderstorm": false,
                    "isSnow": false
                }
            ]
        },
        "wind": {
            "text": "Roof Closed",
            "cssClass": "bg-secondary text-white",
            "arrow": ""
        },
        "roof": true,
        "roofPending": false,
        "lineupHandedness": {},
        "lineupPositions": {}
    },
    {
        "gameRaw": {
            "gamePk": 823877,
            "gameGuid": "0ca55b74-e075-4160-9d92-c290f3e8905f",
            "link": "/api/v1.1/game/823877/feed/live",
            "gameType": "R",
            "season": "2026",
            "gameDate": "2026-05-01T23:10:00Z",
            "officialDate": "2026-05-01",
            "status": {
                "abstractGameState": "Preview",
                "codedGameState": "S",
                "detailedState": "Scheduled",
                "statusCode": "S",
                "startTimeTBD": false,
                "abstractGameCode": "P"
            },
            "teams": {
                "away": {
                    "team": {
                        "id": 143,
                        "name": "Philadelphia Phillies",
                        "link": "/api/v1/teams/143"
                    },
                    "leagueRecord": {
                        "wins": 8,
                        "losses": 18,
                        "pct": ".308"
                    },
                    "splitSquad": false,
                    "seriesNumber": 11
                },
                "home": {
                    "team": {
                        "id": 146,
                        "name": "Miami Marlins",
                        "link": "/api/v1/teams/146"
                    },
                    "leagueRecord": {
                        "wins": 13,
                        "losses": 14,
                        "pct": ".481"
                    },
                    "splitSquad": false,
                    "seriesNumber": 11
                }
            },
            "linescore": {
                "scheduledInnings": 9,
                "innings": [],
                "teams": {
                    "home": {},
                    "away": {}
                },
                "defense": {
                    "team": {
                        "id": 146,
                        "name": "Miami Marlins",
                        "link": "/api/v1/teams/146"
                    }
                },
                "offense": {
                    "team": {
                        "id": 143,
                        "name": "Philadelphia Phillies",
                        "link": "/api/v1/teams/143"
                    }
                }
            },
            "venue": {
                "id": 4169,
                "name": "loanDepot park",
                "link": "/api/v1/venues/4169",
                "active": true,
                "season": "2026"
            },
            "content": {
                "link": "/api/v1/game/823877/content"
            },
            "gameNumber": 1,
            "publicFacing": true,
            "doubleHeader": "N",
            "gamedayType": "P",
            "tiebreaker": "N",
            "calendarEventID": "14-823877-2026-05-01",
            "seasonDisplay": "2026",
            "dayNight": "night",
            "scheduledInnings": 9,
            "reverseHomeAwayStatus": false,
            "inningBreakLength": 120,
            "gamesInSeries": 4,
            "seriesGameNumber": 1,
            "seriesDescription": "Regular Season",
            "recordSource": "S",
            "ifNecessary": "N",
            "ifNecessaryDescription": "Normal Game"
        },
        "stadium": {
            "id": 4169,
            "name": "loanDepot park",
            "team": "Miami Marlins",
            "lat": 25.7783,
            "lon": -80.2196,
            "bearing": 128,
            "roof": true
        },
        "odds": null,
        "weather": {
            "status": "ok",
            "lastUpdated": 1777133745.303741,
            "temp": 84,
            "humidity": 48,
            "maxPrecipChance": 0,
            "isThunderstorm": false,
            "isSnow": false,
            "windSpeed": 13,
            "windDir": 164,
            "hourly": [
                {
                    "timestamp": "2026-05-01T22:00Z",
                    "temp": 85,
                    "precipChance": 0,
                    "isThunderstorm": false,
                    "isSnow": false
                },
                {
                    "timestamp": "2026-05-01T23:00Z",
                    "temp": 84,
                    "precipChance": 0,
                    "isThunderstorm": false,
                    "isSnow": false
                },
                {
                    "timestamp": "2026-05-02T00:00Z",
                    "temp": 84,
                    "precipChance": 0,
                    "isThunderstorm": false,
                    "isSnow": false
                },
                {
                    "timestamp": "2026-05-02T01:00Z",
                    "temp": 83,
                    "precipChance": 0,
                    "isThunderstorm": false,
                    "isSnow": false
                },
                {
                    "timestamp": "2026-05-02T02:00Z",
                    "temp": 82,
                    "precipChance": 0,
                    "isThunderstorm": false,
                    "isSnow": false
                }
            ]
        },
        "wind": {
            "text": "In from Right",
            "cssClass": "bg-in",
            "arrow": "\u2199"
        },
        "roof": false,
        "roofPending": false,
        "lineupHandedness": {},
        "lineupPositions": {}
    },
    {
        "gameRaw": {
            "gamePk": 823713,
            "gameGuid": "79fefb29-9bca-4507-8918-04abc723a458",
            "link": "/api/v1.1/game/823713/feed/live",
            "gameType": "R",
            "season": "2026",
            "gameDate": "2026-05-02T00:10:00Z",
            "officialDate": "2026-05-01",
            "status": {
                "abstractGameState": "Preview",
                "codedGameState": "S",
                "detailedState": "Scheduled",
                "statusCode": "S",
                "startTimeTBD": false,
                "abstractGameCode": "P"
            },
            "teams": {
                "away": {
                    "team": {
                        "id": 141,
                        "name": "Toronto Blue Jays",
                        "link": "/api/v1/teams/141"
                    },
                    "leagueRecord": {
                        "wins": 11,
                        "losses": 15,
                        "pct": ".423"
                    },
                    "splitSquad": false,
                    "seriesNumber": 11
                },
                "home": {
                    "team": {
                        "id": 142,
                        "name": "Minnesota Twins",
                        "link": "/api/v1/teams/142"
                    },
                    "leagueRecord": {
                        "wins": 12,
                        "losses": 15,
                        "pct": ".444"
                    },
                    "splitSquad": false,
                    "seriesNumber": 11
                }
            },
            "linescore": {
                "scheduledInnings": 9,
                "innings": [],
                "teams": {
                    "home": {},
                    "away": {}
                },
                "defense": {
                    "team": {
                        "id": 142,
                        "name": "Minnesota Twins",
                        "link": "/api/v1/teams/142"
                    }
                },
                "offense": {
                    "team": {
                        "id": 141,
                        "name": "Toronto Blue Jays",
                        "link": "/api/v1/teams/141"
                    }
                }
            },
            "venue": {
                "id": 3312,
                "name": "Target Field",
                "link": "/api/v1/venues/3312",
                "active": true,
                "season": "2026"
            },
            "content": {
                "link": "/api/v1/game/823713/content"
            },
            "gameNumber": 1,
            "publicFacing": true,
            "doubleHeader": "N",
            "gamedayType": "P",
            "tiebreaker": "N",
            "calendarEventID": "14-823713-2026-05-01",
            "seasonDisplay": "2026",
            "dayNight": "night",
            "scheduledInnings": 9,
            "reverseHomeAwayStatus": false,
            "inningBreakLength": 120,
            "gamesInSeries": 4,
            "seriesGameNumber": 2,
            "seriesDescription": "Regular Season",
            "recordSource": "S",
            "ifNecessary": "N",
            "ifNecessaryDescription": "Normal Game"
        },
        "stadium": {
            "id": 3312,
            "name": "Target Field",
            "team": "Minnesota Twins",
            "lat": 44.9817,
            "lon": -93.2777,
            "bearing": 45
        },
        "odds": null,
        "weather": {
            "status": "ok",
            "lastUpdated": 1777133746.417563,
            "temp": 55,
            "humidity": 31,
            "maxPrecipChance": 0,
            "isThunderstorm": false,
            "isSnow": false,
            "windSpeed": 7,
            "windDir": 19,
            "hourly": [
                {
                    "timestamp": "2026-05-02T00:00Z",
                    "temp": 55,
                    "precipChance": 0,
                    "isThunderstorm": false,
                    "isSnow": false
                },
                {
                    "timestamp": "2026-05-02T01:00Z",
                    "temp": 54,
                    "precipChance": 0,
                    "isThunderstorm": false,
                    "isSnow": false
                },
                {
                    "timestamp": "2026-05-02T02:00Z",
                    "temp": 52,
                    "precipChance": 0,
                    "isThunderstorm": false,
                    "isSnow": false
                },
                {
                    "timestamp": "2026-05-02T03:00Z",
                    "temp": 51,
                    "precipChance": 0,
                    "isThunderstorm": false,
                    "isSnow": false
                }
            ]
        },
        "wind": {
            "text": "In from Left",
            "cssClass": "bg-in",
            "arrow": "\u2198"
        },
        "roof": false,
        "roofPending": false,
        "lineupHandedness": {},
        "lineupPositions": {}
    },
    {
        "gameRaw": {
            "gamePk": 823066,
            "gameGuid": "5c4db008-296d-4e1b-8c1f-b2700966c5d0",
            "link": "/api/v1.1/game/823066/feed/live",
            "gameType": "R",
            "season": "2026",
            "gameDate": "2026-05-02T00:15:00Z",
            "officialDate": "2026-05-01",
            "status": {
                "abstractGameState": "Preview",
                "codedGameState": "S",
                "detailedState": "Scheduled",
                "statusCode": "S",
                "startTimeTBD": false,
                "abstractGameCode": "P"
            },
            "teams": {
                "away": {
                    "team": {
                        "id": 119,
                        "name": "Los Angeles Dodgers",
                        "link": "/api/v1/teams/119"
                    },
                    "leagueRecord": {
                        "wins": 17,
                        "losses": 9,
                        "pct": ".654"
                    },
                    "splitSquad": false,
                    "seriesNumber": 11
                },
                "home": {
                    "team": {
                        "id": 138,
                        "name": "St. Louis Cardinals",
                        "link": "/api/v1/teams/138"
                    },
                    "leagueRecord": {
                        "wins": 14,
                        "losses": 12,
                        "pct": ".538"
                    },
                    "splitSquad": false,
                    "seriesNumber": 11
                }
            },
            "linescore": {
                "scheduledInnings": 9,
                "innings": [],
                "teams": {
                    "home": {},
                    "away": {}
                },
                "defense": {
                    "team": {
                        "id": 138,
                        "name": "St. Louis Cardinals",
                        "link": "/api/v1/teams/138"
                    }
                },
                "offense": {
                    "team": {
                        "id": 119,
                        "name": "Los Angeles Dodgers",
                        "link": "/api/v1/teams/119"
                    }
                }
            },
            "venue": {
                "id": 2889,
                "name": "Busch Stadium",
                "link": "/api/v1/venues/2889",
                "active": true,
                "season": "2026"
            },
            "content": {
                "link": "/api/v1/game/823066/content"
            },
            "gameNumber": 1,
            "publicFacing": true,
            "doubleHeader": "N",
            "gamedayType": "P",
            "tiebreaker": "N",
            "calendarEventID": "14-823066-2026-05-01",
            "seasonDisplay": "2026",
            "dayNight": "night",
            "scheduledInnings": 9,
            "reverseHomeAwayStatus": false,
            "inningBreakLength": 120,
            "gamesInSeries": 3,
            "seriesGameNumber": 1,
            "seriesDescription": "Regular Season",
            "recordSource": "S",
            "ifNecessary": "N",
            "ifNecessaryDescription": "Normal Game"
        },
        "stadium": {
            "id": 2889,
            "name": "Busch Stadium",
            "team": "St. Louis Cardinals",
            "lat": 38.6226,
            "lon": -90.1928,
            "bearing": 62
        },
        "odds": null,
        "weather": {
            "status": "ok",
            "lastUpdated": 1777133747.531566,
            "temp": 51,
            "humidity": 60,
            "maxPrecipChance": 0,
            "isThunderstorm": false,
            "isSnow": false,
            "windSpeed": 10,
            "windDir": 41,
            "hourly": [
                {
                    "timestamp": "2026-05-02T00:00Z",
                    "temp": 51,
                    "precipChance": 0,
                    "isThunderstorm": false,
                    "isSnow": false
                },
                {
                    "timestamp": "2026-05-02T01:00Z",
                    "temp": 51,
                    "precipChance": 0,
                    "isThunderstorm": false,
                    "isSnow": false
                },
                {
                    "timestamp": "2026-05-02T02:00Z",
                    "temp": 50,
                    "precipChance": 0,
                    "isThunderstorm": false,
                    "isSnow": false
                },
                {
                    "timestamp": "2026-05-02T03:00Z",
                    "temp": 50,
                    "precipChance": 0,
                    "isThunderstorm": false,
                    "isSnow": false
                }
            ]
        },
        "wind": {
            "text": "Blowing IN",
            "cssClass": "bg-in",
            "arrow": "\u2b07"
        },
        "roof": false,
        "roofPending": false,
        "lineupHandedness": {},
        "lineupPositions": {}
    },
    {
        "gameRaw": {
            "gamePk": 824366,
            "gameGuid": "ea2b67fd-3b03-4a42-98ac-9337f5251ca5",
            "link": "/api/v1.1/game/824366/feed/live",
            "gameType": "R",
            "season": "2026",
            "gameDate": "2026-05-02T00:40:00Z",
            "officialDate": "2026-05-01",
            "status": {
                "abstractGameState": "Preview",
                "codedGameState": "S",
                "detailedState": "Scheduled",
                "statusCode": "S",
                "startTimeTBD": false,
                "abstractGameCode": "P"
            },
            "teams": {
                "away": {
                    "team": {
                        "id": 144,
                        "name": "Atlanta Braves",
                        "link": "/api/v1/teams/144"
                    },
                    "leagueRecord": {
                        "wins": 19,
                        "losses": 8,
                        "pct": ".704"
                    },
                    "splitSquad": false,
                    "seriesNumber": 11
                },
                "home": {
                    "team": {
                        "id": 115,
                        "name": "Colorado Rockies",
                        "link": "/api/v1/teams/115"
                    },
                    "leagueRecord": {
                        "wins": 11,
                        "losses": 16,
                        "pct": ".407"
                    },
                    "splitSquad": false,
                    "seriesNumber": 11
                }
            },
            "linescore": {
                "scheduledInnings": 9,
                "innings": [],
                "teams": {
                    "home": {},
                    "away": {}
                },
                "defense": {
                    "team": {
                        "id": 115,
                        "name": "Colorado Rockies",
                        "link": "/api/v1/teams/115"
                    }
                },
                "offense": {
                    "team": {
                        "id": 144,
                        "name": "Atlanta Braves",
                        "link": "/api/v1/teams/144"
                    }
                }
            },
            "venue": {
                "id": 19,
                "name": "Coors Field",
                "link": "/api/v1/venues/19",
                "active": true,
                "season": "2026"
            },
            "content": {
                "link": "/api/v1/game/824366/content"
            },
            "gameNumber": 1,
            "publicFacing": true,
            "doubleHeader": "N",
            "gamedayType": "P",
            "tiebreaker": "N",
            "calendarEventID": "14-824366-2026-05-01",
            "seasonDisplay": "2026",
            "dayNight": "night",
            "scheduledInnings": 9,
            "reverseHomeAwayStatus": false,
            "inningBreakLength": 120,
            "gamesInSeries": 3,
            "seriesGameNumber": 1,
            "seriesDescription": "Regular Season",
            "recordSource": "S",
            "ifNecessary": "N",
            "ifNecessaryDescription": "Normal Game"
        },
        "stadium": {
            "id": 19,
            "name": "Coors Field",
            "team": "Colorado Rockies",
            "lat": 39.7559,
            "lon": -104.9942,
            "bearing": 5
        },
        "odds": null,
        "weather": {
            "status": "ok",
            "lastUpdated": 1777133748.645015,
            "temp": 55,
            "humidity": 27,
            "maxPrecipChance": 0,
            "isThunderstorm": false,
            "isSnow": false,
            "windSpeed": 3,
            "windDir": 168,
            "hourly": [
                {
                    "timestamp": "2026-05-02T00:00Z",
                    "temp": 55,
                    "precipChance": 0,
                    "isThunderstorm": false,
                    "isSnow": false
                },
                {
                    "timestamp": "2026-05-02T01:00Z",
                    "temp": 55,
                    "precipChance": 0,
                    "isThunderstorm": false,
                    "isSnow": false
                },
                {
                    "timestamp": "2026-05-02T02:00Z",
                    "temp": 53,
                    "precipChance": 0,
                    "isThunderstorm": false,
                    "isSnow": false
                },
                {
                    "timestamp": "2026-05-02T03:00Z",
                    "temp": 52,
                    "precipChance": 0,
                    "isThunderstorm": false,
                    "isSnow": false
                }
            ]
        },
        "wind": {
            "text": "Blowing OUT",
            "cssClass": "bg-out",
            "arrow": "\u2b06"
        },
        "roof": false,
        "roofPending": false,
        "lineupHandedness": {},
        "lineupPositions": {}
    },
    {
        "gameRaw": {
            "gamePk": 824041,
            "gameGuid": "e95c95e3-390f-4a54-bd40-ec44395ae54d",
            "link": "/api/v1.1/game/824041/feed/live",
            "gameType": "R",
            "season": "2026",
            "gameDate": "2026-05-02T01:38:00Z",
            "officialDate": "2026-05-01",
            "status": {
                "abstractGameState": "Preview",
                "codedGameState": "S",
                "detailedState": "Scheduled",
                "statusCode": "S",
                "startTimeTBD": false,
                "abstractGameCode": "P"
            },
            "teams": {
                "away": {
                    "team": {
                        "id": 121,
                        "name": "New York Mets",
                        "link": "/api/v1/teams/121"
                    },
                    "leagueRecord": {
                        "wins": 9,
                        "losses": 17,
                        "pct": ".346"
                    },
                    "splitSquad": false,
                    "seriesNumber": 11
                },
                "home": {
                    "team": {
                        "id": 108,
                        "name": "Los Angeles Angels",
                        "link": "/api/v1/teams/108"
                    },
                    "leagueRecord": {
                        "wins": 12,
                        "losses": 15,
                        "pct": ".444"
                    },
                    "splitSquad": false,
                    "seriesNumber": 11
                }
            },
            "linescore": {
                "scheduledInnings": 9,
                "innings": [],
                "teams": {
                    "home": {},
                    "away": {}
                },
                "defense": {
                    "team": {
                        "id": 108,
                        "name": "Los Angeles Angels",
                        "link": "/api/v1/teams/108"
                    }
                },
                "offense": {
                    "team": {
                        "id": 121,
                        "name": "New York Mets",
                        "link": "/api/v1/teams/121"
                    }
                }
            },
            "venue": {
                "id": 1,
                "name": "Angel Stadium",
                "link": "/api/v1/venues/1",
                "active": true,
                "season": "2026"
            },
            "content": {
                "link": "/api/v1/game/824041/content"
            },
            "gameNumber": 1,
            "publicFacing": true,
            "doubleHeader": "N",
            "gamedayType": "P",
            "tiebreaker": "N",
            "calendarEventID": "14-824041-2026-05-01",
            "seasonDisplay": "2026",
            "dayNight": "night",
            "scheduledInnings": 9,
            "reverseHomeAwayStatus": false,
            "inningBreakLength": 120,
            "gamesInSeries": 3,
            "seriesGameNumber": 1,
            "seriesDescription": "Regular Season",
            "recordSource": "S",
            "ifNecessary": "N",
            "ifNecessaryDescription": "Normal Game"
        },
        "stadium": {
            "id": 1,
            "name": "Angel Stadium",
            "team": "Los Angeles Angels",
            "lat": 33.8003,
            "lon": -117.8827,
            "bearing": 45
        },
        "odds": null,
        "weather": {
            "status": "ok",
            "lastUpdated": 1777133749.758679,
            "temp": 70,
            "humidity": 54,
            "maxPrecipChance": 0,
            "isThunderstorm": false,
            "isSnow": false,
            "windSpeed": 8,
            "windDir": 215,
            "hourly": [
                {
                    "timestamp": "2026-05-02T00:00Z",
                    "temp": 72,
                    "precipChance": 0,
                    "isThunderstorm": false,
                    "isSnow": false
                },
                {
                    "timestamp": "2026-05-02T01:00Z",
                    "temp": 70,
                    "precipChance": 0,
                    "isThunderstorm": false,
                    "isSnow": false
                },
                {
                    "timestamp": "2026-05-02T02:00Z",
                    "temp": 68,
                    "precipChance": 0,
                    "isThunderstorm": false,
                    "isSnow": false
                },
                {
                    "timestamp": "2026-05-02T03:00Z",
                    "temp": 66,
                    "precipChance": 0,
                    "isThunderstorm": false,
                    "isSnow": false
                },
                {
                    "timestamp": "2026-05-02T04:00Z",
                    "temp": 65,
                    "precipChance": 0,
                    "isThunderstorm": false,
                    "isSnow": false
                }
            ]
        },
        "wind": {
            "text": "Blowing OUT",
            "cssClass": "bg-out",
            "arrow": "\u2b06"
        },
        "roof": false,
        "roofPending": false,
        "lineupHandedness": {},
        "lineupPositions": {}
    },
    {
        "gameRaw": {
            "gamePk": 825012,
            "gameGuid": "4df18159-63c1-46e8-9a68-cfbc2a25355f",
            "link": "/api/v1.1/game/825012/feed/live",
            "gameType": "R",
            "season": "2026",
            "gameDate": "2026-05-02T01:40:00Z",
            "officialDate": "2026-05-01",
            "status": {
                "abstractGameState": "Preview",
                "codedGameState": "S",
                "detailedState": "Scheduled",
                "statusCode": "S",
                "startTimeTBD": false,
                "abstractGameCode": "P"
            },
            "teams": {
                "away": {
                    "team": {
                        "id": 114,
                        "name": "Cleveland Guardians",
                        "link": "/api/v1/teams/114"
                    },
                    "leagueRecord": {
                        "wins": 15,
                        "losses": 13,
                        "pct": ".536"
                    },
                    "splitSquad": false,
                    "seriesNumber": 11
                },
                "home": {
                    "team": {
                        "id": 133,
                        "name": "Athletics",
                        "link": "/api/v1/teams/133"
                    },
                    "leagueRecord": {
                        "wins": 14,
                        "losses": 12,
                        "pct": ".538"
                    },
                    "splitSquad": false,
                    "seriesNumber": 11
                }
            },
            "linescore": {
                "scheduledInnings": 9,
                "innings": [],
                "teams": {
                    "home": {},
                    "away": {}
                },
                "defense": {
                    "team": {
                        "id": 133,
                        "name": "Athletics",
                        "link": "/api/v1/teams/133"
                    }
                },
                "offense": {
                    "team": {
                        "id": 114,
                        "name": "Cleveland Guardians",
                        "link": "/api/v1/teams/114"
                    }
                }
            },
            "venue": {
                "id": 2529,
                "name": "Sutter Health Park",
                "link": "/api/v1/venues/2529",
                "active": true,
                "season": "2026"
            },
            "content": {
                "link": "/api/v1/game/825012/content"
            },
            "gameNumber": 1,
            "publicFacing": true,
            "doubleHeader": "N",
            "gamedayType": "P",
            "tiebreaker": "N",
            "calendarEventID": "14-825012-2026-05-01",
            "seasonDisplay": "2026",
            "dayNight": "night",
            "scheduledInnings": 9,
            "reverseHomeAwayStatus": false,
            "inningBreakLength": 120,
            "gamesInSeries": 3,
            "seriesGameNumber": 1,
            "seriesDescription": "Regular Season",
            "recordSource": "S",
            "ifNecessary": "N",
            "ifNecessaryDescription": "Normal Game"
        },
        "stadium": {
            "id": 2529,
            "name": "Sutter Health Park",
            "team": "Athletics",
            "lat": 38.5804,
            "lon": -121.5138,
            "bearing": 45
        },
        "odds": null,
        "weather": {
            "status": "ok",
            "lastUpdated": 1777133750.871796,
            "temp": 79,
            "humidity": 44,
            "maxPrecipChance": 0,
            "isThunderstorm": false,
            "isSnow": false,
            "windSpeed": 5,
            "windDir": 197,
            "hourly": [
                {
                    "timestamp": "2026-05-02T00:00Z",
                    "temp": 83,
                    "precipChance": 0,
                    "isThunderstorm": false,
                    "isSnow": false
                },
                {
                    "timestamp": "2026-05-02T01:00Z",
                    "temp": 79,
                    "precipChance": 0,
                    "isThunderstorm": false,
                    "isSnow": false
                },
                {
                    "timestamp": "2026-05-02T02:00Z",
                    "temp": 73,
                    "precipChance": 0,
                    "isThunderstorm": false,
                    "isSnow": false
                },
                {
                    "timestamp": "2026-05-02T03:00Z",
                    "temp": 68,
                    "precipChance": 0,
                    "isThunderstorm": false,
                    "isSnow": false
                },
                {
                    "timestamp": "2026-05-02T04:00Z",
                    "temp": 65,
                    "precipChance": 0,
                    "isThunderstorm": false,
                    "isSnow": false
                }
            ]
        },
        "wind": {
            "text": "Out to Left",
            "cssClass": "bg-out",
            "arrow": "\u2196"
        },
        "roof": false,
        "roofPending": false,
        "lineupHandedness": {},
        "lineupPositions": {}
    },
    {
        "gameRaw": {
            "gamePk": 823309,
            "gameGuid": "367bdb48-0328-4f08-8372-3e9324f36d48",
            "link": "/api/v1.1/game/823309/feed/live",
            "gameType": "R",
            "season": "2026",
            "gameDate": "2026-05-02T01:40:00Z",
            "officialDate": "2026-05-01",
            "status": {
                "abstractGameState": "Preview",
                "codedGameState": "S",
                "detailedState": "Scheduled",
                "statusCode": "S",
                "startTimeTBD": false,
                "abstractGameCode": "P"
            },
            "teams": {
                "away": {
                    "team": {
                        "id": 145,
                        "name": "Chicago White Sox",
                        "link": "/api/v1/teams/145"
                    },
                    "leagueRecord": {
                        "wins": 11,
                        "losses": 16,
                        "pct": ".407"
                    },
                    "splitSquad": false,
                    "seriesNumber": 11
                },
                "home": {
                    "team": {
                        "id": 135,
                        "name": "San Diego Padres",
                        "link": "/api/v1/teams/135"
                    },
                    "leagueRecord": {
                        "wins": 18,
                        "losses": 8,
                        "pct": ".692"
                    },
                    "splitSquad": false,
                    "seriesNumber": 11
                }
            },
            "linescore": {
                "scheduledInnings": 9,
                "innings": [],
                "teams": {
                    "home": {},
                    "away": {}
                },
                "defense": {
                    "team": {
                        "id": 135,
                        "name": "San Diego Padres",
                        "link": "/api/v1/teams/135"
                    }
                },
                "offense": {
                    "team": {
                        "id": 145,
                        "name": "Chicago White Sox",
                        "link": "/api/v1/teams/145"
                    }
                }
            },
            "venue": {
                "id": 2680,
                "name": "Petco Park",
                "link": "/api/v1/venues/2680",
                "active": true,
                "season": "2026"
            },
            "content": {
                "link": "/api/v1/game/823309/content"
            },
            "gameNumber": 1,
            "publicFacing": true,
            "doubleHeader": "N",
            "gamedayType": "P",
            "tiebreaker": "N",
            "calendarEventID": "14-823309-2026-05-01",
            "seasonDisplay": "2026",
            "dayNight": "night",
            "scheduledInnings": 9,
            "reverseHomeAwayStatus": false,
            "inningBreakLength": 120,
            "gamesInSeries": 3,
            "seriesGameNumber": 1,
            "seriesDescription": "Regular Season",
            "recordSource": "S",
            "ifNecessary": "N",
            "ifNecessaryDescription": "Normal Game"
        },
        "stadium": {
            "id": 2680,
            "name": "Petco Park",
            "team": "San Diego Padres",
            "lat": 32.7076,
            "lon": -117.157,
            "bearing": 0
        },
        "odds": null,
        "weather": {
            "status": "ok",
            "lastUpdated": 1777133751.98585,
            "temp": 65,
            "humidity": 66,
            "maxPrecipChance": 0,
            "isThunderstorm": false,
            "isSnow": false,
            "windSpeed": 6,
            "windDir": 242,
            "hourly": [
                {
                    "timestamp": "2026-05-02T00:00Z",
                    "temp": 66,
                    "precipChance": 0,
                    "isThunderstorm": false,
                    "isSnow": false
                },
                {
                    "timestamp": "2026-05-02T01:00Z",
                    "temp": 65,
                    "precipChance": 0,
                    "isThunderstorm": false,
                    "isSnow": false
                },
                {
                    "timestamp": "2026-05-02T02:00Z",
                    "temp": 65,
                    "precipChance": 0,
                    "isThunderstorm": false,
                    "isSnow": false
                },
                {
                    "timestamp": "2026-05-02T03:00Z",
                    "temp": 64,
                    "precipChance": 0,
                    "isThunderstorm": false,
                    "isSnow": false
                },
                {
                    "timestamp": "2026-05-02T04:00Z",
                    "temp": 64,
                    "precipChance": 0,
                    "isThunderstorm": false,
                    "isSnow": false
                }
            ]
        },
        "wind": {
            "text": "Out to Right",
            "cssClass": "bg-out",
            "arrow": "\u2197"
        },
        "roof": false,
        "roofPending": false,
        "lineupHandedness": {},
        "lineupPositions": {}
    },
    {
        "gameRaw": {
            "gamePk": 823146,
            "gameGuid": "1b9a6449-805d-4f1e-90b9-6a6f030f6cdd",
            "link": "/api/v1.1/game/823146/feed/live",
            "gameType": "R",
            "season": "2026",
            "gameDate": "2026-05-02T01:45:00Z",
            "officialDate": "2026-05-01",
            "status": {
                "abstractGameState": "Preview",
                "codedGameState": "S",
                "detailedState": "Scheduled",
                "statusCode": "S",
                "startTimeTBD": false,
                "abstractGameCode": "P"
            },
            "teams": {
                "away": {
                    "team": {
                        "id": 118,
                        "name": "Kansas City Royals",
                        "link": "/api/v1/teams/118"
                    },
                    "leagueRecord": {
                        "wins": 9,
                        "losses": 17,
                        "pct": ".346"
                    },
                    "splitSquad": false,
                    "seriesNumber": 11
                },
                "home": {
                    "team": {
                        "id": 136,
                        "name": "Seattle Mariners",
                        "link": "/api/v1/teams/136"
                    },
                    "leagueRecord": {
                        "wins": 13,
                        "losses": 15,
                        "pct": ".464"
                    },
                    "splitSquad": false,
                    "seriesNumber": 11
                }
            },
            "linescore": {
                "scheduledInnings": 9,
                "innings": [],
                "teams": {
                    "home": {},
                    "away": {}
                },
                "defense": {
                    "team": {
                        "id": 118,
                        "name": "Kansas City Royals",
                        "link": "/api/v1/teams/118"
                    }
                },
                "offense": {
                    "team": {
                        "id": 136,
                        "name": "Seattle Mariners",
                        "link": "/api/v1/teams/136"
                    }
                }
            },
            "venue": {
                "id": 680,
                "name": "T-Mobile Park",
                "link": "/api/v1/venues/680",
                "active": true,
                "season": "2026"
            },
            "content": {
                "link": "/api/v1/game/823146/content"
            },
            "gameNumber": 1,
            "publicFacing": true,
            "doubleHeader": "N",
            "gamedayType": "P",
            "tiebreaker": "N",
            "calendarEventID": "14-823146-2026-05-01",
            "seasonDisplay": "2026",
            "dayNight": "night",
            "scheduledInnings": 9,
            "reverseHomeAwayStatus": false,
            "inningBreakLength": 145,
            "gamesInSeries": 3,
            "seriesGameNumber": 1,
            "seriesDescription": "Regular Season",
            "recordSource": "S",
            "ifNecessary": "N",
            "ifNecessaryDescription": "Normal Game"
        },
        "stadium": {
            "id": 680,
            "name": "T-Mobile Park",
            "team": "Seattle Mariners",
            "lat": 47.5913,
            "lon": -122.3323,
            "bearing": 35,
            "roof": true
        },
        "odds": null,
        "weather": {
            "status": "ok",
            "lastUpdated": 1777133753.099128,
            "temp": 59,
            "humidity": 52,
            "maxPrecipChance": 0,
            "isThunderstorm": false,
            "isSnow": false,
            "windSpeed": 3,
            "windDir": 59,
            "hourly": [
                {
                    "timestamp": "2026-05-02T00:00Z",
                    "temp": 59,
                    "precipChance": 0,
                    "isThunderstorm": false,
                    "isSnow": false
                },
                {
                    "timestamp": "2026-05-02T01:00Z",
                    "temp": 59,
                    "precipChance": 0,
                    "isThunderstorm": false,
                    "isSnow": false
                },
                {
                    "timestamp": "2026-05-02T02:00Z",
                    "temp": 57,
                    "precipChance": 0,
                    "isThunderstorm": false,
                    "isSnow": false
                },
                {
                    "timestamp": "2026-05-02T03:00Z",
                    "temp": 55,
                    "precipChance": 0,
                    "isThunderstorm": false,
                    "isSnow": false
                },
                {
                    "timestamp": "2026-05-02T04:00Z",
                    "temp": 54,
                    "precipChance": 0,
                    "isThunderstorm": false,
                    "isSnow": false
                }
            ]
        },
        "wind": {
            "text": "In from Right",
            "cssClass": "bg-in",
            "arrow": "\u2199"
        },
        "roof": false,
        "roofPending": false,
        "lineupHandedness": {},
        "lineupPositions": {}
    }
]