{
    "last_updated": "2026-02-21T14:28:17.418140+00:00",
    "sport": "baseball_mlb_preseason",
    "game_count": 12,
    "odds": [
        {
            "id": "fa1dd3f5b9b493e1a7754b81b265dcf4",
            "sport_key": "baseball_mlb_preseason",
            "sport_title": "MLB Preseason",
            "commence_time": "2026-02-21T18:05:00Z",
            "home_team": "Tampa Bay Rays",
            "away_team": "Atlanta Braves",
            "bookmakers": [
                {
                    "key": "fanduel",
                    "title": "FanDuel",
                    "last_update": "2026-02-21T14:27:15Z",
                    "markets": [
                        {
                            "key": "h2h",
                            "last_update": "2026-02-21T14:27:15Z",
                            "outcomes": [
                                {
                                    "name": "Atlanta Braves",
                                    "price": 118
                                },
                                {
                                    "name": "Tampa Bay Rays",
                                    "price": -144
                                }
                            ]
                        }
                    ]
                },
                {
                    "key": "betonlineag",
                    "title": "BetOnline.ag",
                    "last_update": "2026-02-21T14:27:46Z",
                    "markets": [
                        {
                            "key": "h2h",
                            "last_update": "2026-02-21T14:27:46Z",
                            "outcomes": [
                                {
                                    "name": "Atlanta Braves",
                                    "price": 135
                                },
                                {
                                    "name": "Tampa Bay Rays",
                                    "price": -155
                                }
                            ]
                        }
                    ]
                },
                {
                    "key": "draftkings",
                    "title": "DraftKings",
                    "last_update": "2026-02-21T14:27:45Z",
                    "markets": [
                        {
                            "key": "h2h",
                            "last_update": "2026-02-21T14:27:45Z",
                            "outcomes": [
                                {
                                    "name": "Atlanta Braves",
                                    "price": 130
                                },
                                {
                                    "name": "Tampa Bay Rays",
                                    "price": -155
                                }
                            ]
                        }
                    ]
                },
                {
                    "key": "betus",
                    "title": "BetUS",
                    "last_update": "2026-02-21T14:27:47Z",
                    "markets": [
                        {
                            "key": "h2h",
                            "last_update": "2026-02-21T14:27:47Z",
                            "outcomes": [
                                {
                                    "name": "Atlanta Braves",
                                    "price": 125
                                },
                                {
                                    "name": "Tampa Bay Rays",
                                    "price": -155
                                }
                            ]
                        }
                    ]
                }
            ]
        },
        {
            "id": "b893defa1feed2d6bc58dbb80a56a412",
            "sport_key": "baseball_mlb_preseason",
            "sport_title": "MLB Preseason",
            "commence_time": "2026-02-21T18:05:00Z",
            "home_team": "Baltimore Orioles",
            "away_team": "Pittsburgh Pirates",
            "bookmakers": [
                {
                    "key": "fanduel",
                    "title": "FanDuel",
                    "last_update": "2026-02-21T14:27:15Z",
                    "markets": [
                        {
                            "key": "h2h",
                            "last_update": "2026-02-21T14:27:15Z",
                            "outcomes": [
                                {
                                    "name": "Baltimore Orioles",
                                    "price": -150
                                },
                                {
                                    "name": "Pittsburgh Pirates",
                                    "price": 122
                                }
                            ]
                        }
                    ]
                },
                {
                    "key": "betonlineag",
                    "title": "BetOnline.ag",
                    "last_update": "2026-02-21T14:27:46Z",
                    "markets": [
                        {
                            "key": "h2h",
                            "last_update": "2026-02-21T14:27:46Z",
                            "outcomes": [
                                {
                                    "name": "Baltimore Orioles",
                                    "price": -140
                                },
                                {
                                    "name": "Pittsburgh Pirates",
                                    "price": 120
                                }
                            ]
                        }
                    ]
                },
                {
                    "key": "draftkings",
                    "title": "DraftKings",
                    "last_update": "2026-02-21T14:27:45Z",
                    "markets": [
                        {
                            "key": "h2h",
                            "last_update": "2026-02-21T14:27:45Z",
                            "outcomes": [
                                {
                                    "name": "Baltimore Orioles",
                                    "price": -142
                                },
                                {
                                    "name": "Pittsburgh Pirates",
                                    "price": 120
                                }
                            ]
                        }
                    ]
                },
                {
                    "key": "betus",
                    "title": "BetUS",
                    "last_update": "2026-02-21T14:27:47Z",
                    "markets": [
                        {
                            "key": "h2h",
                            "last_update": "2026-02-21T14:27:47Z",
                            "outcomes": [
                                {
                                    "name": "Baltimore Orioles",
                                    "price": -140
                                },
                                {
                                    "name": "Pittsburgh Pirates",
                                    "price": 110
                                }
                            ]
                        }
                    ]
                }
            ]
        },
        {
            "id": "e8e3db78d85c080ae64feae56bd3dfc5",
            "sport_key": "baseball_mlb_preseason",
            "sport_title": "MLB Preseason",
            "commence_time": "2026-02-21T18:05:00Z",
            "home_team": "Minnesota Twins",
            "away_team": "Boston Red Sox",
            "bookmakers": [
                {
                    "key": "fanduel",
                    "title": "FanDuel",
                    "last_update": "2026-02-21T14:27:15Z",
                    "markets": [
                        {
                            "key": "h2h",
                            "last_update": "2026-02-21T14:27:15Z",
                            "outcomes": [
                                {
                                    "name": "Boston Red Sox",
                                    "price": -115
                                },
                                {
                                    "name": "Minnesota Twins",
                                    "price": -105
                                }
                            ]
                        }
                    ]
                },
                {
                    "key": "betonlineag",
                    "title": "BetOnline.ag",
                    "last_update": "2026-02-21T14:27:46Z",
                    "markets": [
                        {
                            "key": "h2h",
                            "last_update": "2026-02-21T14:27:46Z",
                            "outcomes": [
                                {
                                    "name": "Boston Red Sox",
                                    "price": -115
                                },
                                {
                                    "name": "Minnesota Twins",
                                    "price": -105
                                }
                            ]
                        }
                    ]
                },
                {
                    "key": "draftkings",
                    "title": "DraftKings",
                    "last_update": "2026-02-21T14:27:45Z",
                    "markets": [
                        {
                            "key": "h2h",
                            "last_update": "2026-02-21T14:27:45Z",
                            "outcomes": [
                                {
                                    "name": "Boston Red Sox",
                                    "price": -112
                                },
                                {
                                    "name": "Minnesota Twins",
                                    "price": -108
                                }
                            ]
                        }
                    ]
                },
                {
                    "key": "betus",
                    "title": "BetUS",
                    "last_update": "2026-02-21T14:27:47Z",
                    "markets": [
                        {
                            "key": "h2h",
                            "last_update": "2026-02-21T14:27:47Z",
                            "outcomes": [
                                {
                                    "name": "Boston Red Sox",
                                    "price": -120
                                },
                                {
                                    "name": "Minnesota Twins",
                                    "price": -110
                                }
                            ]
                        }
                    ]
                }
            ]
        },
        {
            "id": "2c383b0c4004b613aaf9ae643ac0d528",
            "sport_key": "baseball_mlb_preseason",
            "sport_title": "MLB Preseason",
            "commence_time": "2026-02-21T18:05:00Z",
            "home_team": "New York Yankees",
            "away_team": "Detroit Tigers",
            "bookmakers": [
                {
                    "key": "fanduel",
                    "title": "FanDuel",
                    "last_update": "2026-02-21T14:27:15Z",
                    "markets": [
                        {
                            "key": "h2h",
                            "last_update": "2026-02-21T14:27:15Z",
                            "outcomes": [
                                {
                                    "name": "Detroit Tigers",
                                    "price": 128
                                },
                                {
                                    "name": "New York Yankees",
                                    "price": -158
                                }
                            ]
                        }
                    ]
                },
                {
                    "key": "betonlineag",
                    "title": "BetOnline.ag",
                    "last_update": "2026-02-21T14:27:46Z",
                    "markets": [
                        {
                            "key": "h2h",
                            "last_update": "2026-02-21T14:27:46Z",
                            "outcomes": [
                                {
                                    "name": "Detroit Tigers",
                                    "price": 115
                                },
                                {
                                    "name": "New York Yankees",
                                    "price": -135
                                }
                            ]
                        }
                    ]
                },
                {
                    "key": "draftkings",
                    "title": "DraftKings",
                    "last_update": "2026-02-21T14:27:45Z",
                    "markets": [
                        {
                            "key": "h2h",
                            "last_update": "2026-02-21T14:27:45Z",
                            "outcomes": [
                                {
                                    "name": "Detroit Tigers",
                                    "price": 124
                                },
                                {
                                    "name": "New York Yankees",
                                    "price": -148
                                }
                            ]
                        }
                    ]
                },
                {
                    "key": "betus",
                    "title": "BetUS",
                    "last_update": "2026-02-21T14:27:47Z",
                    "markets": [
                        {
                            "key": "h2h",
                            "last_update": "2026-02-21T14:27:47Z",
                            "outcomes": [
                                {
                                    "name": "Detroit Tigers",
                                    "price": 105
                                },
                                {
                                    "name": "New York Yankees",
                                    "price": -135
                                }
                            ]
                        }
                    ]
                }
            ]
        },
        {
            "id": "a0844e6fe41429d7225658ffbff3bfac",
            "sport_key": "baseball_mlb_preseason",
            "sport_title": "MLB Preseason",
            "commence_time": "2026-02-21T18:07:00Z",
            "home_team": "Toronto Blue Jays",
            "away_team": "Philadelphia Phillies",
            "bookmakers": [
                {
                    "key": "fanduel",
                    "title": "FanDuel",
                    "last_update": "2026-02-21T14:27:15Z",
                    "markets": [
                        {
                            "key": "h2h",
                            "last_update": "2026-02-21T14:27:15Z",
                            "outcomes": [
                                {
                                    "name": "Philadelphia Phillies",
                                    "price": 116
                                },
                                {
                                    "name": "Toronto Blue Jays",
                                    "price": -142
                                }
                            ]
                        }
                    ]
                },
                {
                    "key": "betonlineag",
                    "title": "BetOnline.ag",
                    "last_update": "2026-02-21T14:27:46Z",
                    "markets": [
                        {
                            "key": "h2h",
                            "last_update": "2026-02-21T14:27:46Z",
                            "outcomes": [
                                {
                                    "name": "Philadelphia Phillies",
                                    "price": 130
                                },
                                {
                                    "name": "Toronto Blue Jays",
                                    "price": -150
                                }
                            ]
                        }
                    ]
                },
                {
                    "key": "draftkings",
                    "title": "DraftKings",
                    "last_update": "2026-02-21T14:27:45Z",
                    "markets": [
                        {
                            "key": "h2h",
                            "last_update": "2026-02-21T14:27:45Z",
                            "outcomes": [
                                {
                                    "name": "Philadelphia Phillies",
                                    "price": 124
                                },
                                {
                                    "name": "Toronto Blue Jays",
                                    "price": -148
                                }
                            ]
                        }
                    ]
                },
                {
                    "key": "betus",
                    "title": "BetUS",
                    "last_update": "2026-02-21T14:27:47Z",
                    "markets": [
                        {
                            "key": "h2h",
                            "last_update": "2026-02-21T14:27:47Z",
                            "outcomes": [
                                {
                                    "name": "Philadelphia Phillies",
                                    "price": 120
                                },
                                {
                                    "name": "Toronto Blue Jays",
                                    "price": -150
                                }
                            ]
                        }
                    ]
                }
            ]
        },
        {
            "id": "7c60dbc432f437f3e4c914abd729a390",
            "sport_key": "baseball_mlb_preseason",
            "sport_title": "MLB Preseason",
            "commence_time": "2026-02-21T18:10:00Z",
            "home_team": "New York Mets",
            "away_team": "Miami Marlins",
            "bookmakers": [
                {
                    "key": "fanduel",
                    "title": "FanDuel",
                    "last_update": "2026-02-21T14:27:15Z",
                    "markets": [
                        {
                            "key": "h2h",
                            "last_update": "2026-02-21T14:27:15Z",
                            "outcomes": [
                                {
                                    "name": "Miami Marlins",
                                    "price": 122
                                },
                                {
                                    "name": "New York Mets",
                                    "price": -150
                                }
                            ]
                        }
                    ]
                },
                {
                    "key": "betonlineag",
                    "title": "BetOnline.ag",
                    "last_update": "2026-02-21T14:27:46Z",
                    "markets": [
                        {
                            "key": "h2h",
                            "last_update": "2026-02-21T14:27:46Z",
                            "outcomes": [
                                {
                                    "name": "Miami Marlins",
                                    "price": 125
                                },
                                {
                                    "name": "New York Mets",
                                    "price": -145
                                }
                            ]
                        }
                    ]
                },
                {
                    "key": "draftkings",
                    "title": "DraftKings",
                    "last_update": "2026-02-21T14:27:45Z",
                    "markets": [
                        {
                            "key": "h2h",
                            "last_update": "2026-02-21T14:27:45Z",
                            "outcomes": [
                                {
                                    "name": "Miami Marlins",
                                    "price": 124
                                },
                                {
                                    "name": "New York Mets",
                                    "price": -148
                                }
                            ]
                        }
                    ]
                },
                {
                    "key": "betus",
                    "title": "BetUS",
                    "last_update": "2026-02-21T14:27:47Z",
                    "markets": [
                        {
                            "key": "h2h",
                            "last_update": "2026-02-21T14:27:47Z",
                            "outcomes": [
                                {
                                    "name": "Miami Marlins",
                                    "price": 115
                                },
                                {
                                    "name": "New York Mets",
                                    "price": -145
                                }
                            ]
                        }
                    ]
                }
            ]
        },
        {
            "id": "5afb8fe9cde900e3baff33b76d32811b",
            "sport_key": "baseball_mlb_preseason",
            "sport_title": "MLB Preseason",
            "commence_time": "2026-02-21T20:05:00Z",
            "home_team": "Chicago White Sox",
            "away_team": "Athletics",
            "bookmakers": [
                {
                    "key": "fanduel",
                    "title": "FanDuel",
                    "last_update": "2026-02-21T14:27:15Z",
                    "markets": [
                        {
                            "key": "h2h",
                            "last_update": "2026-02-21T14:27:15Z",
                            "outcomes": [
                                {
                                    "name": "Athletics",
                                    "price": -110
                                },
                                {
                                    "name": "Chicago White Sox",
                                    "price": -110
                                }
                            ]
                        }
                    ]
                },
                {
                    "key": "betonlineag",
                    "title": "BetOnline.ag",
                    "last_update": "2026-02-21T14:27:46Z",
                    "markets": [
                        {
                            "key": "h2h",
                            "last_update": "2026-02-21T14:27:46Z",
                            "outcomes": [
                                {
                                    "name": "Athletics",
                                    "price": -110
                                },
                                {
                                    "name": "Chicago White Sox",
                                    "price": -110
                                }
                            ]
                        }
                    ]
                },
                {
                    "key": "draftkings",
                    "title": "DraftKings",
                    "last_update": "2026-02-21T14:27:45Z",
                    "markets": [
                        {
                            "key": "h2h",
                            "last_update": "2026-02-21T14:27:45Z",
                            "outcomes": [
                                {
                                    "name": "Athletics",
                                    "price": -110
                                },
                                {
                                    "name": "Chicago White Sox",
                                    "price": -110
                                }
                            ]
                        }
                    ]
                },
                {
                    "key": "betus",
                    "title": "BetUS",
                    "last_update": "2026-02-21T14:27:47Z",
                    "markets": [
                        {
                            "key": "h2h",
                            "last_update": "2026-02-21T14:27:47Z",
                            "outcomes": [
                                {
                                    "name": "Athletics",
                                    "price": -115
                                },
                                {
                                    "name": "Chicago White Sox",
                                    "price": -115
                                }
                            ]
                        }
                    ]
                }
            ]
        },
        {
            "id": "e8e453d44b44dd3bb77b4675fc051ca5",
            "sport_key": "baseball_mlb_preseason",
            "sport_title": "MLB Preseason",
            "commence_time": "2026-02-21T20:05:00Z",
            "home_team": "Chicago Cubs",
            "away_team": "Texas Rangers",
            "bookmakers": [
                {
                    "key": "fanduel",
                    "title": "FanDuel",
                    "last_update": "2026-02-21T14:27:15Z",
                    "markets": [
                        {
                            "key": "h2h",
                            "last_update": "2026-02-21T14:27:15Z",
                            "outcomes": [
                                {
                                    "name": "Chicago Cubs",
                                    "price": -132
                                },
                                {
                                    "name": "Texas Rangers",
                                    "price": 108
                                }
                            ]
                        }
                    ]
                },
                {
                    "key": "betonlineag",
                    "title": "BetOnline.ag",
                    "last_update": "2026-02-21T14:27:46Z",
                    "markets": [
                        {
                            "key": "h2h",
                            "last_update": "2026-02-21T14:27:46Z",
                            "outcomes": [
                                {
                                    "name": "Chicago Cubs",
                                    "price": -130
                                },
                                {
                                    "name": "Texas Rangers",
                                    "price": 110
                                }
                            ]
                        }
                    ]
                },
                {
                    "key": "draftkings",
                    "title": "DraftKings",
                    "last_update": "2026-02-21T14:27:45Z",
                    "markets": [
                        {
                            "key": "h2h",
                            "last_update": "2026-02-21T14:27:45Z",
                            "outcomes": [
                                {
                                    "name": "Chicago Cubs",
                                    "price": -130
                                },
                                {
                                    "name": "Texas Rangers",
                                    "price": 110
                                }
                            ]
                        }
                    ]
                },
                {
                    "key": "betus",
                    "title": "BetUS",
                    "last_update": "2026-02-21T14:27:47Z",
                    "markets": [
                        {
                            "key": "h2h",
                            "last_update": "2026-02-21T14:27:47Z",
                            "outcomes": [
                                {
                                    "name": "Chicago Cubs",
                                    "price": -130
                                },
                                {
                                    "name": "Texas Rangers",
                                    "price": 100
                                }
                            ]
                        }
                    ]
                }
            ]
        },
        {
            "id": "37483f55e5b3c245b58b3950fb7fb72a",
            "sport_key": "baseball_mlb_preseason",
            "sport_title": "MLB Preseason",
            "commence_time": "2026-02-21T20:05:00Z",
            "home_team": "Kansas City Royals",
            "away_team": "San Diego Padres",
            "bookmakers": [
                {
                    "key": "fanduel",
                    "title": "FanDuel",
                    "last_update": "2026-02-21T14:27:15Z",
                    "markets": [
                        {
                            "key": "h2h",
                            "last_update": "2026-02-21T14:27:15Z",
                            "outcomes": [
                                {
                                    "name": "Kansas City Royals",
                                    "price": -120
                                },
                                {
                                    "name": "San Diego Padres",
                                    "price": -102
                                }
                            ]
                        }
                    ]
                },
                {
                    "key": "betonlineag",
                    "title": "BetOnline.ag",
                    "last_update": "2026-02-21T14:27:46Z",
                    "markets": [
                        {
                            "key": "h2h",
                            "last_update": "2026-02-21T14:27:46Z",
                            "outcomes": [
                                {
                                    "name": "Kansas City Royals",
                                    "price": -135
                                },
                                {
                                    "name": "San Diego Padres",
                                    "price": 115
                                }
                            ]
                        }
                    ]
                },
                {
                    "key": "draftkings",
                    "title": "DraftKings",
                    "last_update": "2026-02-21T14:27:45Z",
                    "markets": [
                        {
                            "key": "h2h",
                            "last_update": "2026-02-21T14:27:45Z",
                            "outcomes": [
                                {
                                    "name": "Kansas City Royals",
                                    "price": -120
                                },
                                {
                                    "name": "San Diego Padres",
                                    "price": 100
                                }
                            ]
                        }
                    ]
                },
                {
                    "key": "betus",
                    "title": "BetUS",
                    "last_update": "2026-02-21T14:27:47Z",
                    "markets": [
                        {
                            "key": "h2h",
                            "last_update": "2026-02-21T14:27:47Z",
                            "outcomes": [
                                {
                                    "name": "Kansas City Royals",
                                    "price": -135
                                },
                                {
                                    "name": "San Diego Padres",
                                    "price": 105
                                }
                            ]
                        }
                    ]
                }
            ]
        },
        {
            "id": "1ee9c1f5d938ad4bfdc43f849e41d286",
            "sport_key": "baseball_mlb_preseason",
            "sport_title": "MLB Preseason",
            "commence_time": "2026-02-21T20:10:00Z",
            "home_team": "Arizona Diamondbacks",
            "away_team": "Colorado Rockies",
            "bookmakers": [
                {
                    "key": "fanduel",
                    "title": "FanDuel",
                    "last_update": "2026-02-21T14:27:15Z",
                    "markets": [
                        {
                            "key": "h2h",
                            "last_update": "2026-02-21T14:27:15Z",
                            "outcomes": [
                                {
                                    "name": "Arizona Diamondbacks",
                                    "price": -160
                                },
                                {
                                    "name": "Colorado Rockies",
                                    "price": 130
                                }
                            ]
                        }
                    ]
                },
                {
                    "key": "betonlineag",
                    "title": "BetOnline.ag",
                    "last_update": "2026-02-21T14:27:46Z",
                    "markets": [
                        {
                            "key": "h2h",
                            "last_update": "2026-02-21T14:27:46Z",
                            "outcomes": [
                                {
                                    "name": "Arizona Diamondbacks",
                                    "price": -145
                                },
                                {
                                    "name": "Colorado Rockies",
                                    "price": 125
                                }
                            ]
                        }
                    ]
                },
                {
                    "key": "draftkings",
                    "title": "DraftKings",
                    "last_update": "2026-02-21T14:27:45Z",
                    "markets": [
                        {
                            "key": "h2h",
                            "last_update": "2026-02-21T14:27:45Z",
                            "outcomes": [
                                {
                                    "name": "Arizona Diamondbacks",
                                    "price": -155
                                },
                                {
                                    "name": "Colorado Rockies",
                                    "price": 130
                                }
                            ]
                        }
                    ]
                },
                {
                    "key": "betus",
                    "title": "BetUS",
                    "last_update": "2026-02-21T14:27:47Z",
                    "markets": [
                        {
                            "key": "h2h",
                            "last_update": "2026-02-21T14:27:47Z",
                            "outcomes": [
                                {
                                    "name": "Arizona Diamondbacks",
                                    "price": -145
                                },
                                {
                                    "name": "Colorado Rockies",
                                    "price": 115
                                }
                            ]
                        }
                    ]
                }
            ]
        },
        {
            "id": "ef234aa34593030aca36e19b396ed5bd",
            "sport_key": "baseball_mlb_preseason",
            "sport_title": "MLB Preseason",
            "commence_time": "2026-02-21T20:10:00Z",
            "home_team": "Los Angeles Angels",
            "away_team": "Los Angeles Dodgers",
            "bookmakers": [
                {
                    "key": "fanduel",
                    "title": "FanDuel",
                    "last_update": "2026-02-21T14:27:15Z",
                    "markets": [
                        {
                            "key": "h2h",
                            "last_update": "2026-02-21T14:27:15Z",
                            "outcomes": [
                                {
                                    "name": "Los Angeles Angels",
                                    "price": 132
                                },
                                {
                                    "name": "Los Angeles Dodgers",
                                    "price": -162
                                }
                            ]
                        }
                    ]
                },
                {
                    "key": "betonlineag",
                    "title": "BetOnline.ag",
                    "last_update": "2026-02-21T14:27:46Z",
                    "markets": [
                        {
                            "key": "h2h",
                            "last_update": "2026-02-21T14:27:46Z",
                            "outcomes": [
                                {
                                    "name": "Los Angeles Angels",
                                    "price": 135
                                },
                                {
                                    "name": "Los Angeles Dodgers",
                                    "price": -155
                                }
                            ]
                        }
                    ]
                },
                {
                    "key": "draftkings",
                    "title": "DraftKings",
                    "last_update": "2026-02-21T14:27:45Z",
                    "markets": [
                        {
                            "key": "h2h",
                            "last_update": "2026-02-21T14:27:45Z",
                            "outcomes": [
                                {
                                    "name": "Los Angeles Angels",
                                    "price": 130
                                },
                                {
                                    "name": "Los Angeles Dodgers",
                                    "price": -155
                                }
                            ]
                        }
                    ]
                },
                {
                    "key": "betus",
                    "title": "BetUS",
                    "last_update": "2026-02-21T14:27:47Z",
                    "markets": [
                        {
                            "key": "h2h",
                            "last_update": "2026-02-21T14:27:47Z",
                            "outcomes": [
                                {
                                    "name": "Los Angeles Angels",
                                    "price": 125
                                },
                                {
                                    "name": "Los Angeles Dodgers",
                                    "price": -155
                                }
                            ]
                        }
                    ]
                }
            ]
        },
        {
            "id": "dcf7bbe149cfb247e1211af58c43d05c",
            "sport_key": "baseball_mlb_preseason",
            "sport_title": "MLB Preseason",
            "commence_time": "2026-02-21T20:10:00Z",
            "home_team": "Seattle Mariners",
            "away_team": "San Francisco Giants",
            "bookmakers": [
                {
                    "key": "fanduel",
                    "title": "FanDuel",
                    "last_update": "2026-02-21T14:27:15Z",
                    "markets": [
                        {
                            "key": "h2h",
                            "last_update": "2026-02-21T14:27:15Z",
                            "outcomes": [
                                {
                                    "name": "San Francisco Giants",
                                    "price": 118
                                },
                                {
                                    "name": "Seattle Mariners",
                                    "price": -144
                                }
                            ]
                        }
                    ]
                },
                {
                    "key": "betonlineag",
                    "title": "BetOnline.ag",
                    "last_update": "2026-02-21T14:27:46Z",
                    "markets": [
                        {
                            "key": "h2h",
                            "last_update": "2026-02-21T14:27:46Z",
                            "outcomes": [
                                {
                                    "name": "San Francisco Giants",
                                    "price": 115
                                },
                                {
                                    "name": "Seattle Mariners",
                                    "price": -135
                                }
                            ]
                        }
                    ]
                },
                {
                    "key": "draftkings",
                    "title": "DraftKings",
                    "last_update": "2026-02-21T14:27:45Z",
                    "markets": [
                        {
                            "key": "h2h",
                            "last_update": "2026-02-21T14:27:45Z",
                            "outcomes": [
                                {
                                    "name": "San Francisco Giants",
                                    "price": 120
                                },
                                {
                                    "name": "Seattle Mariners",
                                    "price": -142
                                }
                            ]
                        }
                    ]
                },
                {
                    "key": "betus",
                    "title": "BetUS",
                    "last_update": "2026-02-21T14:27:47Z",
                    "markets": [
                        {
                            "key": "h2h",
                            "last_update": "2026-02-21T14:27:47Z",
                            "outcomes": [
                                {
                                    "name": "San Francisco Giants",
                                    "price": 105
                                },
                                {
                                    "name": "Seattle Mariners",
                                    "price": -135
                                }
                            ]
                        }
                    ]
                }
            ]
        }
    ]
}